{
  "quotes": {
    "MCD": {
      "symbol": "MCD",
      "price": 301.83,
      "change": -1.74,
      "changePercent": -0.57,
      "isPositive": false,
      "isNegative": true,
      "high": 304.26,
      "low": 300.81,
      "open": 304.26,
      "previousClose": 303.57,
      "timestamp": 1764689003,
      "source": "finnhub"
    },
    "YUM": {
      "symbol": "YUM",
      "price": 149.13,
      "change": -1.51,
      "changePercent": -1.0,
      "isPositive": false,
      "isNegative": true,
      "high": 151.33,
      "low": 149.11,
      "open": 151.33,
      "previousClose": 150.64,
      "timestamp": 1764688980,
      "source": "finnhub"
    },
    "QSR": {
      "symbol": "QSR",
      "price": 71.63,
      "change": 0.02,
      "changePercent": 0.03,
      "isPositive": true,
      "isNegative": false,
      "high": 72.25,
      "low": 71.5,
      "open": 71.92,
      "previousClose": 71.61,
      "timestamp": 1764688981,
      "source": "finnhub"
    },
    "WEN": {
      "symbol": "WEN",
      "price": 8.07,
      "change": -0.16,
      "changePercent": -1.89,
      "isPositive": false,
      "isNegative": true,
      "high": 8.24,
      "low": 8.02,
      "open": 8.24,
      "previousClose": 8.23,
      "timestamp": 1764688998,
      "source": "finnhub"
    },
    "DPZ": {
      "symbol": "DPZ",
      "price": 427.87,
      "change": 4.02,
      "changePercent": 0.95,
      "isPositive": true,
      "isNegative": false,
      "high": 427.87,
      "low": 420.01,
      "open": 426.39,
      "previousClose": 423.85,
      "timestamp": 1764688988,
      "source": "finnhub"
    },
    "JACK": {
      "symbol": "JACK",
      "price": 19.18,
      "change": -0.14,
      "changePercent": -0.7,
      "isPositive": false,
      "isNegative": true,
      "high": 19.3,
      "low": 18.61,
      "open": 19.05,
      "previousClose": 19.32,
      "timestamp": 1764688927,
      "source": "finnhub"
    },
    "WING": {
      "symbol": "WING",
      "price": 277.57,
      "change": 8.34,
      "changePercent": 3.1,
      "isPositive": true,
      "isNegative": false,
      "high": 279.8,
      "low": 270.56,
      "open": 270.56,
      "previousClose": 269.23,
      "timestamp": 1764689048,
      "source": "finnhub"
    },
    "SHAK": {
      "symbol": "SHAK",
      "price": 86.63,
      "change": 0.51,
      "changePercent": 0.59,
      "isPositive": true,
      "isNegative": false,
      "high": 87.77,
      "low": 86.38,
      "open": 87,
      "previousClose": 86.12,
      "timestamp": 1764689009,
      "source": "finnhub"
    },
    "DENN": {
      "symbol": "DENN",
      "price": 6.18,
      "change": 0.0,
      "changePercent": 0.08,
      "isPositive": true,
      "isNegative": false,
      "high": 6.19,
      "low": 6.18,
      "open": 6.18,
      "previousClose": 6.18,
      "timestamp": 1764689042,
      "source": "finnhub"
    },
    "DIN": {
      "symbol": "DIN",
      "price": 30.37,
      "change": 0.22,
      "changePercent": 0.73,
      "isPositive": true,
      "isNegative": false,
      "high": 30.6,
      "low": 30.01,
      "open": 30.01,
      "previousClose": 30.15,
      "timestamp": 1764688993,
      "source": "finnhub"
    },
    "DNUT": {
      "symbol": "DNUT",
      "price": 4.13,
      "change": -0.01,
      "changePercent": -0.16,
      "isPositive": false,
      "isNegative": true,
      "high": 4.16,
      "low": 4.06,
      "open": 4.14,
      "previousClose": 4.14,
      "timestamp": 1764689046,
      "source": "finnhub"
    },
    "NATH": {
      "symbol": "NATH",
      "price": 92.76,
      "change": 1.05,
      "changePercent": 1.14,
      "isPositive": true,
      "isNegative": false,
      "high": 93.61,
      "low": 92.25,
      "open": 92.86,
      "previousClose": 91.71,
      "timestamp": 1764688771,
      "source": "finnhub"
    },
    "RRGB": {
      "symbol": "RRGB",
      "price": 4.07,
      "change": -0.15,
      "changePercent": -3.54,
      "isPositive": false,
      "isNegative": true,
      "high": 4.22,
      "low": 4.07,
      "open": 4.17,
      "previousClose": 4.22,
      "timestamp": 1764688996,
      "source": "finnhub"
    },
    "DRVN": {
      "symbol": "DRVN",
      "price": 13.9,
      "change": -0.23,
      "changePercent": -1.63,
      "isPositive": false,
      "isNegative": true,
      "high": 14.18,
      "low": 13.62,
      "open": 13.98,
      "previousClose": 14.13,
      "timestamp": 1764689036,
      "source": "finnhub"
    },
    "HRB": {
      "symbol": "HRB",
      "price": 42.25,
      "change": 0.01,
      "changePercent": 0.03,
      "isPositive": true,
      "isNegative": false,
      "high": 42.44,
      "low": 41.81,
      "open": 42.01,
      "previousClose": 42.24,
      "timestamp": 1764689007,
      "source": "finnhub"
    },
    "MCW": {
      "symbol": "MCW",
      "price": 5.23,
      "change": -0.08,
      "changePercent": -1.51,
      "isPositive": false,
      "isNegative": true,
      "high": 5.31,
      "low": 5.18,
      "open": 5.25,
      "previousClose": 5.31,
      "timestamp": 1764689024,
      "source": "finnhub"
    },
    "SERV": {
      "symbol": "SERV",
      "price": 9.97,
      "change": 0.24,
      "changePercent": 2.47,
      "isPositive": true,
      "isNegative": false,
      "high": 10,
      "low": 9.74,
      "open": 9.86,
      "previousClose": 9.73,
      "timestamp": 1764689045,
      "source": "finnhub"
    },
    "ROL": {
      "symbol": "ROL",
      "price": 60.82,
      "change": -0.36,
      "changePercent": -0.59,
      "isPositive": false,
      "isNegative": true,
      "high": 61.57,
      "low": 60.58,
      "open": 61.4,
      "previousClose": 61.18,
      "timestamp": 1764689042,
      "source": "finnhub"
    },
    "PLNT": {
      "symbol": "PLNT",
      "price": 111.1,
      "change": 2.1,
      "changePercent": 1.93,
      "isPositive": true,
      "isNegative": false,
      "high": 111.39,
      "low": 109.57,
      "open": 109.81,
      "previousClose": 109,
      "timestamp": 1764689026,
      "source": "finnhub"
    },
    "MAR": {
      "symbol": "MAR",
      "price": 300.44,
      "change": -3.0,
      "changePercent": -0.99,
      "isPositive": false,
      "isNegative": true,
      "high": 304.56,
      "low": 300.1,
      "open": 303.99,
      "previousClose": 303.44,
      "timestamp": 1764689055,
      "source": "finnhub"
    },
    "HLT": {
      "symbol": "HLT",
      "price": 278.29,
      "change": -4.75,
      "changePercent": -1.68,
      "isPositive": false,
      "isNegative": true,
      "high": 283.67,
      "low": 278.18,
      "open": 283.32,
      "previousClose": 283.04,
      "timestamp": 1764689049,
      "source": "finnhub"
    },
    "H": {
      "symbol": "H",
      "price": 158.91,
      "change": -2.24,
      "changePercent": -1.39,
      "isPositive": false,
      "isNegative": true,
      "high": 162.43,
      "low": 158.65,
      "open": 161.08,
      "previousClose": 161.15,
      "timestamp": 1764689050,
      "source": "finnhub"
    },
    "CHH": {
      "symbol": "CHH",
      "price": 88.19,
      "change": -1.12,
      "changePercent": -1.25,
      "isPositive": false,
      "isNegative": true,
      "high": 89.89,
      "low": 87.9,
      "open": 89.32,
      "previousClose": 89.31,
      "timestamp": 1764689029,
      "source": "finnhub"
    },
    "WH": {
      "symbol": "WH",
      "price": 72.18,
      "change": -0.73,
      "changePercent": -1.0,
      "isPositive": false,
      "isNegative": true,
      "high": 73.31,
      "low": 72.09,
      "open": 73.18,
      "previousClose": 72.91,
      "timestamp": 1764688986,
      "source": "finnhub"
    },
    "VAC": {
      "symbol": "VAC",
      "price": 54.08,
      "change": -0.88,
      "changePercent": -1.6,
      "isPositive": false,
      "isNegative": true,
      "high": 55.39,
      "low": 54.05,
      "open": 55.01,
      "previousClose": 54.96,
      "timestamp": 1764689023,
      "source": "finnhub"
    },
    "TNL": {
      "symbol": "TNL",
      "price": 67.58,
      "change": -0.53,
      "changePercent": -0.78,
      "isPositive": false,
      "isNegative": true,
      "high": 68.48,
      "low": 67.45,
      "open": 67.8,
      "previousClose": 68.11,
      "timestamp": 1764688911,
      "source": "finnhub"
    },
    "RENT": {
      "symbol": "RENT",
      "price": 4.86,
      "change": -0.01,
      "changePercent": -0.3,
      "isPositive": false,
      "isNegative": true,
      "high": 4.9,
      "low": 4.78,
      "open": 4.88,
      "previousClose": 4.87,
      "timestamp": 1764689017,
      "source": "finnhub"
    },
    "ADUS": {
      "symbol": "ADUS",
      "price": 120.83,
      "change": -0.01,
      "changePercent": -0.01,
      "isPositive": false,
      "isNegative": true,
      "high": 121.09,
      "low": 120.19,
      "open": 120.97,
      "previousClose": 120.84,
      "timestamp": 1764688489,
      "source": "finnhub"
    },
    "LOPE": {
      "symbol": "LOPE",
      "price": 157.62,
      "change": -0.44,
      "changePercent": -0.28,
      "isPositive": false,
      "isNegative": true,
      "high": 158.06,
      "low": 155.9,
      "open": 157.2,
      "previousClose": 158.06,
      "timestamp": 1764689032,
      "source": "finnhub"
    },
    "PLAY": {
      "symbol": "PLAY",
      "price": 17.39,
      "change": -0.14,
      "changePercent": -0.83,
      "isPositive": false,
      "isNegative": true,
      "high": 17.52,
      "low": 17.04,
      "open": 17.28,
      "previousClose": 17.53,
      "timestamp": 1764689049,
      "source": "finnhub"
    },
    "ARCO": {
      "symbol": "ARCO",
      "price": 7.51,
      "change": -0.0,
      "changePercent": -0.07,
      "isPositive": false,
      "isNegative": true,
      "high": 7.56,
      "low": 7.45,
      "open": 7.56,
      "previousClose": 7.52,
      "timestamp": 1764689052,
      "source": "finnhub"
    }
  },
  "fetchedAt": "2025-12-02T15:24:55.721080Z",
  "count": 31,
  "source": "finnhub"
}