{
  "quotes": {
    "MCD": {
      "symbol": "MCD",
      "price": 321.14,
      "change": 2.45,
      "changePercent": 0.77,
      "isPositive": true,
      "isNegative": false,
      "high": 321.74,
      "low": 317.5,
      "open": 317.5,
      "previousClose": 318.69,
      "timestamp": 1766075420,
      "source": "finnhub"
    },
    "YUM": {
      "symbol": "YUM",
      "price": 154.31,
      "change": 1.18,
      "changePercent": 0.77,
      "isPositive": true,
      "isNegative": false,
      "high": 154.66,
      "low": 152.71,
      "open": 153.1,
      "previousClose": 153.14,
      "timestamp": 1766075399,
      "source": "finnhub"
    },
    "QSR": {
      "symbol": "QSR",
      "price": 70.4,
      "change": 0.2,
      "changePercent": 0.28,
      "isPositive": true,
      "isNegative": false,
      "high": 70.86,
      "low": 69.64,
      "open": 69.64,
      "previousClose": 70.2,
      "timestamp": 1766075421,
      "source": "finnhub"
    },
    "WEN": {
      "symbol": "WEN",
      "price": 8.45,
      "change": -0.04,
      "changePercent": -0.53,
      "isPositive": false,
      "isNegative": true,
      "high": 8.53,
      "low": 8.4,
      "open": 8.53,
      "previousClose": 8.49,
      "timestamp": 1766075410,
      "source": "finnhub"
    },
    "DPZ": {
      "symbol": "DPZ",
      "price": 438.5,
      "change": 0.08,
      "changePercent": 0.02,
      "isPositive": true,
      "isNegative": false,
      "high": 442.35,
      "low": 437.45,
      "open": 438,
      "previousClose": 438.42,
      "timestamp": 1766075399,
      "source": "finnhub"
    },
    "JACK": {
      "symbol": "JACK",
      "price": 19.61,
      "change": 0.1,
      "changePercent": 0.51,
      "isPositive": true,
      "isNegative": false,
      "high": 19.96,
      "low": 19.52,
      "open": 19.58,
      "previousClose": 19.51,
      "timestamp": 1766075394,
      "source": "finnhub"
    },
    "WING": {
      "symbol": "WING",
      "price": 253.13,
      "change": 5.69,
      "changePercent": 2.3,
      "isPositive": true,
      "isNegative": false,
      "high": 256.2,
      "low": 250,
      "open": 252,
      "previousClose": 247.44,
      "timestamp": 1766075416,
      "source": "finnhub"
    },
    "SHAK": {
      "symbol": "SHAK",
      "price": 86.29,
      "change": 4.0,
      "changePercent": 4.86,
      "isPositive": true,
      "isNegative": false,
      "high": 88.5,
      "low": 84.34,
      "open": 84.34,
      "previousClose": 82.29,
      "timestamp": 1766075410,
      "source": "finnhub"
    },
    "DENN": {
      "symbol": "DENN",
      "price": 6.21,
      "change": 0.0,
      "changePercent": 0.08,
      "isPositive": true,
      "isNegative": false,
      "high": 6.22,
      "low": 6.21,
      "open": 6.22,
      "previousClose": 6.21,
      "timestamp": 1766075410,
      "source": "finnhub"
    },
    "DIN": {
      "symbol": "DIN",
      "price": 34.83,
      "change": 0.89,
      "changePercent": 2.62,
      "isPositive": true,
      "isNegative": false,
      "high": 35.13,
      "low": 34.35,
      "open": 34.4,
      "previousClose": 33.94,
      "timestamp": 1766075277,
      "source": "finnhub"
    },
    "DNUT": {
      "symbol": "DNUT",
      "price": 4.62,
      "change": 0.16,
      "changePercent": 3.62,
      "isPositive": true,
      "isNegative": false,
      "high": 4.68,
      "low": 4.51,
      "open": 4.56,
      "previousClose": 4.46,
      "timestamp": 1766075407,
      "source": "finnhub"
    },
    "NATH": {
      "symbol": "NATH",
      "price": 98.6,
      "change": 1.66,
      "changePercent": 1.71,
      "isPositive": true,
      "isNegative": false,
      "high": 99.07,
      "low": 97.09,
      "open": 97.65,
      "previousClose": 96.94,
      "timestamp": 1766075282,
      "source": "finnhub"
    },
    "RRGB": {
      "symbol": "RRGB",
      "price": 4.04,
      "change": 0.05,
      "changePercent": 1.25,
      "isPositive": true,
      "isNegative": false,
      "high": 4.13,
      "low": 4.03,
      "open": 4.06,
      "previousClose": 3.99,
      "timestamp": 1766075289,
      "source": "finnhub"
    },
    "DRVN": {
      "symbol": "DRVN",
      "price": 15.57,
      "change": 0.22,
      "changePercent": 1.47,
      "isPositive": true,
      "isNegative": false,
      "high": 15.68,
      "low": 15.44,
      "open": 15.46,
      "previousClose": 15.35,
      "timestamp": 1766075285,
      "source": "finnhub"
    },
    "HRB": {
      "symbol": "HRB",
      "price": 43.77,
      "change": -0.18,
      "changePercent": -0.41,
      "isPositive": false,
      "isNegative": true,
      "high": 43.99,
      "low": 43.31,
      "open": 43.45,
      "previousClose": 43.95,
      "timestamp": 1766075405,
      "source": "finnhub"
    },
    "MCW": {
      "symbol": "MCW",
      "price": 5.79,
      "change": 0.04,
      "changePercent": 0.78,
      "isPositive": true,
      "isNegative": false,
      "high": 5.82,
      "low": 5.72,
      "open": 5.74,
      "previousClose": 5.75,
      "timestamp": 1766075328,
      "source": "finnhub"
    },
    "SERV": {
      "symbol": "SERV",
      "price": 10.05,
      "change": 0.5,
      "changePercent": 5.29,
      "isPositive": true,
      "isNegative": false,
      "high": 10.55,
      "low": 9.8,
      "open": 9.8,
      "previousClose": 9.55,
      "timestamp": 1766075421,
      "source": "finnhub"
    },
    "ROL": {
      "symbol": "ROL",
      "price": 60.77,
      "change": 0.53,
      "changePercent": 0.88,
      "isPositive": true,
      "isNegative": false,
      "high": 60.95,
      "low": 59.99,
      "open": 60,
      "previousClose": 60.24,
      "timestamp": 1766075399,
      "source": "finnhub"
    },
    "PLNT": {
      "symbol": "PLNT",
      "price": 110.39,
      "change": 0.39,
      "changePercent": 0.35,
      "isPositive": true,
      "isNegative": false,
      "high": 111.45,
      "low": 109.67,
      "open": 110.5,
      "previousClose": 110,
      "timestamp": 1766075422,
      "source": "finnhub"
    },
    "MAR": {
      "symbol": "MAR",
      "price": 307.64,
      "change": -2.43,
      "changePercent": -0.78,
      "isPositive": false,
      "isNegative": true,
      "high": 311.69,
      "low": 306.42,
      "open": 310.09,
      "previousClose": 310.07,
      "timestamp": 1766075421,
      "source": "finnhub"
    },
    "HLT": {
      "symbol": "HLT",
      "price": 288.7,
      "change": -4.3,
      "changePercent": -1.47,
      "isPositive": false,
      "isNegative": true,
      "high": 294.92,
      "low": 288.65,
      "open": 294.09,
      "previousClose": 293,
      "timestamp": 1766075423,
      "source": "finnhub"
    },
    "H": {
      "symbol": "H",
      "price": 161.65,
      "change": -2.63,
      "changePercent": -1.6,
      "isPositive": false,
      "isNegative": true,
      "high": 165.65,
      "low": 161.4,
      "open": 165.2,
      "previousClose": 164.28,
      "timestamp": 1766075411,
      "source": "finnhub"
    },
    "CHH": {
      "symbol": "CHH",
      "price": 92.84,
      "change": -2.37,
      "changePercent": -2.49,
      "isPositive": false,
      "isNegative": true,
      "high": 96.01,
      "low": 92.39,
      "open": 95.21,
      "previousClose": 95.21,
      "timestamp": 1766075416,
      "source": "finnhub"
    },
    "WH": {
      "symbol": "WH",
      "price": 78.44,
      "change": -2.05,
      "changePercent": -2.55,
      "isPositive": false,
      "isNegative": true,
      "high": 81.29,
      "low": 78.32,
      "open": 80.59,
      "previousClose": 80.49,
      "timestamp": 1766075422,
      "source": "finnhub"
    },
    "VAC": {
      "symbol": "VAC",
      "price": 58.32,
      "change": 0.2,
      "changePercent": 0.34,
      "isPositive": true,
      "isNegative": false,
      "high": 59.05,
      "low": 58.19,
      "open": 58.88,
      "previousClose": 58.12,
      "timestamp": 1766075328,
      "source": "finnhub"
    },
    "TNL": {
      "symbol": "TNL",
      "price": 71.57,
      "change": -0.12,
      "changePercent": -0.16,
      "isPositive": false,
      "isNegative": true,
      "high": 72.3,
      "low": 71.26,
      "open": 72.11,
      "previousClose": 71.69,
      "timestamp": 1766075374,
      "source": "finnhub"
    },
    "RENT": {
      "symbol": "RENT",
      "price": 8.98,
      "change": 0.24,
      "changePercent": 2.76,
      "isPositive": true,
      "isNegative": false,
      "high": 9.2,
      "low": 8.66,
      "open": 8.75,
      "previousClose": 8.74,
      "timestamp": 1766075303,
      "source": "finnhub"
    },
    "ADUS": {
      "symbol": "ADUS",
      "price": 112.36,
      "change": -0.62,
      "changePercent": -0.54,
      "isPositive": false,
      "isNegative": true,
      "high": 114.32,
      "low": 112.08,
      "open": 114.32,
      "previousClose": 112.98,
      "timestamp": 1766075292,
      "source": "finnhub"
    },
    "LOPE": {
      "symbol": "LOPE",
      "price": 167.24,
      "change": 1.35,
      "changePercent": 0.81,
      "isPositive": true,
      "isNegative": false,
      "high": 167.24,
      "low": 164.83,
      "open": 165.46,
      "previousClose": 165.89,
      "timestamp": 1766075210,
      "source": "finnhub"
    },
    "PLAY": {
      "symbol": "PLAY",
      "price": 18.43,
      "change": -0.11,
      "changePercent": -0.59,
      "isPositive": false,
      "isNegative": true,
      "high": 18.75,
      "low": 18.4,
      "open": 18.54,
      "previousClose": 18.54,
      "timestamp": 1766075423,
      "source": "finnhub"
    },
    "ARCO": {
      "symbol": "ARCO",
      "price": 7.39,
      "change": 0.14,
      "changePercent": 1.93,
      "isPositive": true,
      "isNegative": false,
      "high": 7.4,
      "low": 7.25,
      "open": 7.34,
      "previousClose": 7.25,
      "timestamp": 1766075423,
      "source": "finnhub"
    }
  },
  "fetchedAt": "2025-12-18T16:31:19.310166Z",
  "count": 31,
  "source": "finnhub"
}