{
  "fetchedAt": "2025-12-19T14:46:15.639442Z",
  "totalSymbols": 40,
  "successCount": 40,
  "errorCount": 0,
  "errors": [],
  "quotes": {
    "MCD": {
      "symbol": "MCD",
      "price": 318.46,
      "previousClose": 319.74,
      "change": -1.28,
      "changePercent": -0.4,
      "name": "McDonald's Corporation",
      "marketCap": 227258023936,
      "volume": 1145688
    },
    "YUM": {
      "symbol": "YUM",
      "price": 154.97,
      "previousClose": 154.68,
      "change": 0.29,
      "changePercent": 0.19,
      "name": "Yum! Brands, Inc.",
      "marketCap": 43027861504,
      "volume": 319259
    },
    "QSR": {
      "symbol": "QSR",
      "price": 70.16,
      "previousClose": 69.9,
      "change": 0.26,
      "changePercent": 0.37,
      "name": "Restaurant Brands International",
      "marketCap": 32066705408,
      "volume": 57120
    },
    "WEN": {
      "symbol": "WEN",
      "price": 8.3,
      "previousClose": 8.44,
      "change": -0.13,
      "changePercent": -1.6,
      "name": "Wendy's Company (The)",
      "marketCap": 1582643200,
      "volume": 497553
    },
    "DPZ": {
      "symbol": "DPZ",
      "price": 433.22,
      "previousClose": 431.37,
      "change": 1.85,
      "changePercent": 0.43,
      "name": "Domino's Pizza Inc",
      "marketCap": 14707436544,
      "volume": 58131
    },
    "JACK": {
      "symbol": "JACK",
      "price": 19.59,
      "previousClose": 19.68,
      "change": -0.09,
      "changePercent": -0.46,
      "name": "Jack In The Box Inc.",
      "marketCap": 369908480,
      "volume": 24146
    },
    "WING": {
      "symbol": "WING",
      "price": 254.92,
      "previousClose": 254.53,
      "change": 0.39,
      "changePercent": 0.15,
      "name": "Wingstop Inc.",
      "marketCap": 7118323200,
      "volume": 64066
    },
    "SHAK": {
      "symbol": "SHAK",
      "price": 86.08,
      "previousClose": 86.35,
      "change": -0.27,
      "changePercent": -0.31,
      "name": "Shake Shack, Inc.",
      "marketCap": 3675045888,
      "volume": 94484
    },
    "CMG": {
      "symbol": "CMG",
      "price": 37.2,
      "previousClose": 37.62,
      "change": -0.42,
      "changePercent": -1.13,
      "name": "Chipotle Mexican Grill, Inc.",
      "marketCap": 49874214912,
      "volume": 2427809
    },
    "SBUX": {
      "symbol": "SBUX",
      "price": 88.72,
      "previousClose": 89.42,
      "change": -0.7,
      "changePercent": -0.78,
      "name": "Starbucks Corporation",
      "marketCap": 100883513344,
      "volume": 2148874
    },
    "PZZA": {
      "symbol": "PZZA",
      "price": 40.59,
      "previousClose": 40.77,
      "change": -0.18,
      "changePercent": -0.43,
      "name": "Papa John's International, Inc.",
      "marketCap": 1331086336,
      "volume": 35584
    },
    "DNUT": {
      "symbol": "DNUT",
      "price": 4.68,
      "previousClose": 4.64,
      "change": 0.04,
      "changePercent": 0.86,
      "name": "Krispy Kreme, Inc.",
      "marketCap": 801683968,
      "volume": 205065
    },
    "NATH": {
      "symbol": "NATH",
      "price": 96.91,
      "previousClose": 98.12,
      "change": -1.21,
      "changePercent": -1.23,
      "name": "Nathan's Famous, Inc.",
      "marketCap": 396314432,
      "volume": 3440
    },
    "DENN": {
      "symbol": "DENN",
      "price": 6.21,
      "previousClose": 6.21,
      "change": 0.0,
      "changePercent": 0.0,
      "name": "Denny's Corporation",
      "marketCap": 319808768,
      "volume": 231107
    },
    "DIN": {
      "symbol": "DIN",
      "price": 34.41,
      "previousClose": 34.49,
      "change": -0.09,
      "changePercent": -0.25,
      "name": "Dine Brands Global, Inc. Common",
      "marketCap": 529125600,
      "volume": 23440
    },
    "RRGB": {
      "symbol": "RRGB",
      "price": 4.08,
      "previousClose": 4.1,
      "change": -0.02,
      "changePercent": -0.49,
      "name": "Red Robin Gourmet Burgers, Inc.",
      "marketCap": 73294992,
      "volume": 6097
    },
    "TXRH": {
      "symbol": "TXRH",
      "price": 174.9,
      "previousClose": 174.25,
      "change": 0.65,
      "changePercent": 0.37,
      "name": "Texas Roadhouse, Inc.",
      "marketCap": 11622211584,
      "volume": 109631
    },
    "CAKE": {
      "symbol": "CAKE",
      "price": 51.22,
      "previousClose": 51.66,
      "change": -0.44,
      "changePercent": -0.86,
      "name": "The Cheesecake Factory Incorpor",
      "marketCap": 2552642048,
      "volume": 63530
    },
    "DRI": {
      "symbol": "DRI",
      "price": 189.05,
      "previousClose": 192.9,
      "change": -3.84,
      "changePercent": -1.99,
      "name": "Darden Restaurants, Inc.",
      "marketCap": 22042267648,
      "volume": 275906
    },
    "EAT": {
      "symbol": "EAT",
      "price": 147.99,
      "previousClose": 150.61,
      "change": -2.62,
      "changePercent": -1.74,
      "name": "Brinker International, Inc.",
      "marketCap": 6575153664,
      "volume": 47658
    },
    "BLMN": {
      "symbol": "BLMN",
      "price": 7.0,
      "previousClose": 7.18,
      "change": -0.18,
      "changePercent": -2.51,
      "name": "Bloomin' Brands, Inc.",
      "marketCap": 596519616,
      "volume": 145108
    },
    "PLAY": {
      "symbol": "PLAY",
      "price": 17.7,
      "previousClose": 18.03,
      "change": -0.33,
      "changePercent": -1.8,
      "name": "Dave & Buster's Entertainment, ",
      "marketCap": 614014080,
      "volume": 69683
    },
    "MAR": {
      "symbol": "MAR",
      "price": 308.99,
      "previousClose": 306.82,
      "change": 2.17,
      "changePercent": 0.71,
      "name": "Marriott International",
      "marketCap": 83876388864,
      "volume": 542847
    },
    "HLT": {
      "symbol": "HLT",
      "price": 289.35,
      "previousClose": 287.63,
      "change": 1.72,
      "changePercent": 0.6,
      "name": "Hilton Worldwide Holdings Inc.",
      "marketCap": 68053315584,
      "volume": 298690
    },
    "H": {
      "symbol": "H",
      "price": 162.92,
      "previousClose": 162.48,
      "change": 0.44,
      "changePercent": 0.27,
      "name": "Hyatt Hotels Corporation",
      "marketCap": 15556414464,
      "volume": 34140
    },
    "CHH": {
      "symbol": "CHH",
      "price": 95.23,
      "previousClose": 94.99,
      "change": 0.25,
      "changePercent": 0.26,
      "name": "Choice Hotels International, In",
      "marketCap": 4406772736,
      "volume": 31312
    },
    "WH": {
      "symbol": "WH",
      "price": 78.98,
      "previousClose": 79.45,
      "change": -0.47,
      "changePercent": -0.59,
      "name": "Wyndham Hotels & Resorts, Inc.",
      "marketCap": 6030616576,
      "volume": 92284
    },
    "IHG": {
      "symbol": "IHG",
      "price": 142.61,
      "previousClose": 140.48,
      "change": 2.13,
      "changePercent": 1.52,
      "name": "Intercontinental Hotels Group",
      "marketCap": 21491763200,
      "volume": 19314
    },
    "VAC": {
      "symbol": "VAC",
      "price": 57.47,
      "previousClose": 57.65,
      "change": -0.18,
      "changePercent": -0.32,
      "name": "Marriott Vacations Worldwide Co",
      "marketCap": 1989092992,
      "volume": 35604
    },
    "TNL": {
      "symbol": "TNL",
      "price": 71.52,
      "previousClose": 71.45,
      "change": 0.07,
      "changePercent": 0.1,
      "name": "Travel   Leisure Co.",
      "marketCap": 4649330688,
      "volume": 55131
    },
    "DRVN": {
      "symbol": "DRVN",
      "price": 15.24,
      "previousClose": 15.34,
      "change": -0.1,
      "changePercent": -0.65,
      "name": "Driven Brands Holdings Inc.",
      "marketCap": 2506282240,
      "volume": 43252
    },
    "HRB": {
      "symbol": "HRB",
      "price": 43.17,
      "previousClose": 43.29,
      "change": -0.12,
      "changePercent": -0.27,
      "name": "H&R Block, Inc.",
      "marketCap": 5520697344,
      "volume": 113904
    },
    "MCW": {
      "symbol": "MCW",
      "price": 5.74,
      "previousClose": 5.71,
      "change": 0.03,
      "changePercent": 0.44,
      "name": "Mister Car Wash, Inc.",
      "marketCap": 1878604672,
      "volume": 87462
    },
    "SERV": {
      "symbol": "SERV",
      "price": 10.27,
      "previousClose": 10.12,
      "change": 0.15,
      "changePercent": 1.43,
      "name": "Serve Robotics Inc.",
      "marketCap": 764572928,
      "volume": 545900
    },
    "ROL": {
      "symbol": "ROL",
      "price": 59.76,
      "previousClose": 60.19,
      "change": -0.43,
      "changePercent": -0.71,
      "name": "Rollins, Inc.",
      "marketCap": 28753557504,
      "volume": 413797
    },
    "PLNT": {
      "symbol": "PLNT",
      "price": 110.71,
      "previousClose": 110.06,
      "change": 0.65,
      "changePercent": 0.59,
      "name": "Planet Fitness, Inc.",
      "marketCap": 9325496320,
      "volume": 63049
    },
    "XPOF": {
      "symbol": "XPOF",
      "price": 7.56,
      "previousClose": 7.6,
      "change": -0.04,
      "changePercent": -0.53,
      "name": "Xponential Fitness, Inc.",
      "marketCap": 369736928,
      "volume": 17221
    },
    "ARCO": {
      "symbol": "ARCO",
      "price": 7.26,
      "previousClose": 7.25,
      "change": 0.01,
      "changePercent": 0.14,
      "name": "Arcos Dorados Holdings Inc.",
      "marketCap": 1529413888,
      "volume": 18256
    },
    "ADUS": {
      "symbol": "ADUS",
      "price": 110.69,
      "previousClose": 112.07,
      "change": -1.38,
      "changePercent": -1.23,
      "name": "Addus HomeCare Corporation",
      "marketCap": 2046005760,
      "volume": 14523
    },
    "LOPE": {
      "symbol": "LOPE",
      "price": 165.38,
      "previousClose": 164.84,
      "change": 0.54,
      "changePercent": 0.33,
      "name": "Grand Canyon Education, Inc.",
      "marketCap": 4645063168,
      "volume": 23630
    }
  }
}