[
  {
    "ticker": "CMG",
    "price": 38.9,
    "change": 1.47,
    "changePercent": 3.94,
    "timestamp": "2026-01-06T14:49:54.899341"
  },
  {
    "ticker": "SBUX",
    "price": 87.95,
    "change": 4.45,
    "changePercent": 5.33,
    "timestamp": "2026-01-06T14:49:55.075376"
  },
  {
    "ticker": "MCD",
    "price": 300.36,
    "change": -0.89,
    "changePercent": -0.3,
    "timestamp": "2026-01-06T14:49:55.426156"
  },
  {
    "ticker": "WEN",
    "price": 8.32,
    "change": 0.21,
    "changePercent": 2.59,
    "timestamp": "2026-01-06T14:49:55.587848"
  },
  {
    "ticker": "WING",
    "price": 261.45,
    "change": 5.39,
    "changePercent": 2.1,
    "timestamp": "2026-01-06T14:49:55.703660"
  },
  {
    "ticker": "SHAK",
    "price": 87.5,
    "change": 4.27,
    "changePercent": 5.13,
    "timestamp": "2026-01-06T14:49:55.793346"
  },
  {
    "ticker": "DPZ",
    "price": 410.05,
    "change": -0.45,
    "changePercent": -0.11,
    "timestamp": "2026-01-06T14:49:55.939497"
  }
]